AUTHORS.rst
CONTRIBUTING.rst
HISTORY.rst
LICENSE
MANIFEST.in
README.md
README.rst
setup.cfg
setup.py
docs/Makefile
docs/authors.rst
docs/conf.py
docs/contributing.rst
docs/history.rst
docs/index.rst
docs/installation.rst
docs/make.bat
docs/readme.rst
docs/usage.rst
igs/__init__.py
igs/cli.py
igs/igs.py
igs.egg-info/PKG-INFO
igs.egg-info/SOURCES.txt
igs.egg-info/dependency_links.txt
igs.egg-info/entry_points.txt
igs.egg-info/not-zip-safe
igs.egg-info/requires.txt
igs.egg-info/top_level.txt
tests/__init__.py
tests/test_igs.py