Metadata-Version: 1.1
Name: igs
Version: 0.1.0
Summary: If i had an iges I would .. in the morning.
Home-page: https://github.com/lepy/igs
Author: lepy
Author-email: lepy@mailbox.org
License: MIT license
Keywords: igs
Platform: UNKNOWN
Classifier: Development Status :: 2 - Pre-Alpha
Classifier: Intended Audience :: Developers
Classifier: License :: OSI Approved :: MIT License
Classifier: Natural Language :: English
Classifier: Programming Language :: Python :: 2
Classifier: Programming Language :: Python :: 2.6
Classifier: Programming Language :: Python :: 2.7
Classifier: Programming Language :: Python :: 3
Classifier: Programming Language :: Python :: 3.3
Classifier: Programming Language :: Python :: 3.4
Classifier: Programming Language :: Python :: 3.5
